qviewer/__init__.py
qviewer/main.py
qviewer/viewer.c
qviewer/viewer.cp311-win_amd64.pyd
qviewer/viewer.pyx
qviewer-1.0.1.dist-info/licenses/LICENSE
qviewer-1.0.1.dist-info/METADATA
qviewer-1.0.1.dist-info/WHEEL
qviewer-1.0.1.dist-info/entry_points.txt
qviewer-1.0.1.dist-info/top_level.txt
qviewer-1.0.1.dist-info/RECORD
