Metadata-Version: 2.4
Name: qviewer
Version: 1.0.1
Summary: A fast PyQt5-based image viewer with URL support and navigation
Home-page: https://github.com/cumulus13/qviewer
Author: Hadi Cahyadi
Author-email: Hadi Cahyadi <cumulus13@gmail.com>
License: MIT
Project-URL: Homepage, https://github.com/cumulus13/qviewer
Project-URL: Repository, https://github.com/cumulus13/qviewer
Keywords: image,viewer,pyqt5,navigation,gui
Classifier: Development Status :: 4 - Beta
Classifier: Intended Audience :: End Users/Desktop
Classifier: Topic :: Multimedia :: Graphics :: Viewers
Classifier: Programming Language :: Python :: 3
Classifier: Programming Language :: Python :: 3.7
Classifier: Programming Language :: Python :: 3.8
Classifier: Programming Language :: Python :: 3.9
Classifier: Programming Language :: Python :: 3.10
Classifier: Programming Language :: Python :: 3.11
Classifier: Programming Language :: Cython
Requires-Python: >=3.7
License-File: LICENSE
Requires-Dist: PyQt5>=5.15.0
Requires-Dist: requests>=2.25.0
Requires-Dist: clipboard>=0.0.4
Dynamic: author
Dynamic: home-page
Dynamic: license-file
Dynamic: requires-python
